partnershipparser/__init__.py
partnershipparser/main.py
partnershipparser/prompts.py
partnershipparser-2025.12.21231803.dist-info/METADATA
partnershipparser-2025.12.21231803.dist-info/WHEEL
partnershipparser-2025.12.21231803.dist-info/top_level.txt
partnershipparser-2025.12.21231803.dist-info/RECORD
