Metadata-Version: 2.4
Name: partnershipparser
Version: 2025.12.21231803
Summary: partnershipparser extracts and structures key info from tech partnership news for easy analysis of companies, focus areas, and impacts
Author-email: partnershipparser <hi@eugene.plus>
License: MIT
Project-URL: Homepage, https://github.com/chigwell/partnershipparser
Requires-Python: >=3.9
Requires-Dist: langchain-llm7>=0.0.0
Requires-Dist: llmatch-messages>=0.0.0
Requires-Dist: langchain-core>=0.3.0
